{
  "version": "0.1.0",
  "name": "houses_token_keeper",
  "instructions": [
    {
      "name": "output",
      "accounts": [
        {
          "name": "tokenProgram",
          "isMut": false,
          "isSigner": false
        },
        {
          "name": "systemProgram",
          "isMut": false,
          "isSigner": false
        },
        {
          "name": "associatedTokenProgram",
          "isMut": false,
          "isSigner": false
        },
        {
          "name": "tokenMint",
          "isMut": false,
          "isSigner": false
        },
        {
          "name": "userPda",
          "isMut": true,
          "isSigner": false
        },
        {
          "name": "userPdaTokenAccount",
          "isMut": true,
          "isSigner": false
        },
        {
          "name": "recipient",
          "isMut": false,
          "isSigner": false
        },
        {
          "name": "recipientTokenAccount",
          "isMut": true,
          "isSigner": false
        },
        {
          "name": "authority",
          "isMut": true,
          "isSigner": true
        }
      ],
      "args": [
        {
          "name": "email",
          "type": "string"
        },
        {
          "name": "amount",
          "type": "u64"
        }
      ]
    },
    {
      "name": "stake",
      "accounts": [
        {
          "name": "tokenProgram",
          "isMut": false,
          "isSigner": false
        },
        {
          "name": "systemProgram",
          "isMut": false,
          "isSigner": false
        },
        {
          "name": "associatedTokenProgram",
          "isMut": false,
          "isSigner": false
        },
        {
          "name": "stakeProgram",
          "isMut": false,
          "isSigner": false
        },
        {
          "name": "tokenMint",
          "isMut": false,
          "isSigner": false
        },
        {
          "name": "userPda",
          "isMut": true,
          "isSigner": false
        },
        {
          "name": "userPdaTokenAccount",
          "isMut": true,
          "isSigner": false
        },
        {
          "name": "stakePda",
          "isMut": true,
          "isSigner": false
        },
        {
          "name": "stakeTokenAccount",
          "isMut": true,
          "isSigner": false
        },
        {
          "name": "dataPda",
          "isMut": true,
          "isSigner": false
        },
        {
          "name": "authority",
          "isMut": true,
          "isSigner": true
        }
      ],
      "args": [
        {
          "name": "email",
          "type": "string"
        },
        {
          "name": "amount",
          "type": "u64"
        }
      ]
    },
    {
      "name": "unstake",
      "accounts": [
        {
          "name": "tokenProgram",
          "isMut": false,
          "isSigner": false
        },
        {
          "name": "systemProgram",
          "isMut": false,
          "isSigner": false
        },
        {
          "name": "associatedTokenProgram",
          "isMut": false,
          "isSigner": false
        },
        {
          "name": "stakeProgram",
          "isMut": false,
          "isSigner": false
        },
        {
          "name": "tokenMint",
          "isMut": true,
          "isSigner": false
        },
        {
          "name": "userPda",
          "isMut": true,
          "isSigner": false
        },
        {
          "name": "userPdaTokenAccount",
          "isMut": true,
          "isSigner": false
        },
        {
          "name": "stakePda",
          "isMut": true,
          "isSigner": false
        },
        {
          "name": "stakeTokenAccount",
          "isMut": true,
          "isSigner": false
        },
        {
          "name": "dataPda",
          "isMut": true,
          "isSigner": false
        },
        {
          "name": "authority",
          "isMut": true,
          "isSigner": true
        }
      ],
      "args": [
        {
          "name": "email",
          "type": "string"
        },
        {
          "name": "amount",
          "type": "u64"
        }
      ]
    },
    {
      "name": "claimReward",
      "accounts": [
        {
          "name": "tokenProgram",
          "isMut": false,
          "isSigner": false
        },
        {
          "name": "systemProgram",
          "isMut": false,
          "isSigner": false
        },
        {
          "name": "associatedTokenProgram",
          "isMut": false,
          "isSigner": false
        },
        {
          "name": "stakeProgram",
          "isMut": false,
          "isSigner": false
        },
        {
          "name": "tokenMint",
          "isMut": false,
          "isSigner": false
        },
        {
          "name": "rewardMint",
          "isMut": false,
          "isSigner": false
        },
        {
          "name": "stakePda",
          "isMut": true,
          "isSigner": false
        },
        {
          "name": "dataPda",
          "isMut": true,
          "isSigner": false
        },
        {
          "name": "rewardTokenAccount",
          "isMut": true,
          "isSigner": false
        },
        {
          "name": "userRewardTokenAccount",
          "isMut": true,
          "isSigner": false
        },
        {
          "name": "userPda",
          "isMut": true,
          "isSigner": false
        },
        {
          "name": "authority",
          "isMut": true,
          "isSigner": true
        }
      ],
      "args": [
        {
          "name": "email",
          "type": "string"
        }
      ]
    }
  ],
  "accounts": [
    {
      "name": "UserPda",
      "type": {
        "kind": "struct",
        "fields": [
          {
            "name": "bump",
            "type": "u8"
          }
        ]
      }
    }
  ],
  "metadata": {
    "address": "BnHCabsYvwUPEkd22RMbk2y5g8XSgbhU435yGVik12vc"
  }
}